<step title="Incoming Request" date="2024-03-10T17:15:23.763" instance="e8252b"
      url="/api/zipdeploy?isAsync=true&amp;deployer=GITHUB_ZIP_DEPLOY&amp;message=%7B%22type%22%3A%22deployment%22%2C%22sha%22%3A%2236a80180ff3dc70850e974d0dfd74927cadda89c%22%2C%22repoName%22%3A%22Dean99712%2Fbadatsoccer-server%22%2C%22actor%22%3A%22Dean99712%22%2C%22slotName%22%3A%22Production%22%2C%22commitMessage%22%3A%22update%20app.yaml%22%7D"
      method="POST" type="request" pid="87,1,20" Host="python-flask-webapp-t.scm.azurewebsites.net"
      User-Agent="GITHUBACTIONS_DeployWebAppToAzure_cc89b21438b02de564a4dc08852f9df2c502643db9e806b29bc1ef2b741b9b6d"
      Authorization="Bas..." Content-Type="application/octet-stream"
      Cookie="ARRAffinity=e8252b7aac8c616f4523d0e298e83724f29ed838d140ac780eeaa9c45cadf4a5;Path=/;HttpOnly;Secure;Domain=python-flask-webapp-t.scm.azurewebsites.net; ARRAffinitySameSite=e8252b7aac8c616f4523d0e298e83724f29ed838d140ac780eeaa9c45cadf4a5;Path=/;HttpOnly;SameSite=None;Secure;Domain=python-flask-webapp-t.scm.azurewebsites.net"
      Transfer-Encoding="chunked" X-ARR-LOG-ID="2cc649bb-dbb1-42be-b837-c1c1db2ce06c" CLIENT-IP="172.183.53.141:26628"
      X-Client-IP="172.183.53.141" X-SITE-DEPLOYMENT-ID="python-flask-webapp-t"
      WAS-DEFAULT-HOSTNAME="python-flask-webapp-t.scm.azurewebsites.net" X-Forwarded-Proto="https"
      X-AppService-Proto="https" X-Forwarded-TlsVersion="1.3"
      X-WAWS-Unencoded-URL="/api/zipdeploy?isAsync=true&amp;deployer=GITHUB_ZIP_DEPLOY&amp;message=%7B%22type%22%3A%22deployment%22%2C%22sha%22%3A%2236a80180ff3dc70850e974d0dfd74927cadda89c%22%2C%22repoName%22%3A%22Dean99712%2Fbadatsoccer-server%22%2C%22actor%22%3A%22Dean99712%22%2C%22slotName%22%3A%22Production%22%2C%22commitMessage%22%3A%22update%20app.yaml%22%7D"
      X-Client-Port="26628">
    <step title="ZipPushDeploy" date="2024-03-10T17:15:23.886">
        <step title="ZipDeploy. Extract zip. Remote build." date="2024-03-10T17:15:23.899"/><!-- duration: 8ms -->
        <step title="None repository commit" date="2024-03-10T17:15:23.957">
            <step title="Commit id: d4ae022c-175f-48cf-b54b-eb7d2ac334e3" date="2024-03-10T17:15:23.965" Message="N/A"
                  AuthorName="N/A" AuthorEmail="N/A"/><!-- duration: 8ms -->
        </step><!-- duration: 18ms -->
        <step title="Removing previous build artifact&apos;s manifest file" date="2024-03-10T17:15:23.996">
            <step title="Writing artifact to /tmp/zipdeploy/62bd883f-d1ea-49f9-a552-ffd765e79041.zip"
                  date="2024-03-10T17:15:24.171"/><!-- duration: 203ms -->
            <step title="Start deployment in the background" date="2024-03-10T17:15:24.442">
                <step title="Acquiring Deployment Lock" date="2024-03-10T17:15:24.470"/><!-- duration: 11ms -->
                <step title="Acquired Deployment Lock" date="2024-03-10T17:15:24.563"/><!-- duration: 2ms -->
            </step><!-- duration: 1223ms -->
        </step><!-- duration: 1686ms -->
        <step title="Outgoing response" date="2024-03-10T17:15:25.692" type="response" statusCode="202"
              statusText="Accepted"/><!-- duration: 3ms -->
    </step><!-- duration: 1811ms -->
